{
  "cloud": {
    "ref": "cloud",
    "name": "Cloud Strife",
    "image": "cloud.png",
    "hp_base": 14,
    "xp_formula": "x*30",
    "weapon": "buster-sword",
    "inTeam": true
  },
  "barret": {
    "ref": "barret",
    "name": "Barret Wallace",
    "image": "barret.png",
    "hp_base": 16,
    "xp_formula": "x*30-2",
    "weapon": "gatling-gun",
    "inTeam": true
  },
  "tifa": {
    "ref": "tifa",
    "name": "Tifa Lockhart",
    "image": "tifa.png",
    "hp_base": 13,
    "xp_formula": "x*30-4",
    "weapon": "leather-glove",
    "inTeam": true
  },
  "aerith": {
    "ref": "aerith",
    "name": "Aerith Gainsborough",
    "image": "aerith.png",
    "hp_base": 12,
    "xp_formula": "x*30+2",
    "weapon": "guard-stick"
  },
  "redxiii": {
    "ref": "redxiii",
    "name": "Red XIII",
    "image": "redxiii.png",
    "hp_base": 17,
    "xp_formula": "x*30-1",
    "weapon": "mythril-clip"
  }
}